tabularxls/__init__.py
tabularxls/main.py
tabularxls/tabular_utils.py
tabular2xls-0.4.6.dist-info/AUTHORS.rst
tabular2xls-0.4.6.dist-info/LICENSE.txt
tabular2xls-0.4.6.dist-info/METADATA
tabular2xls-0.4.6.dist-info/WHEEL
tabular2xls-0.4.6.dist-info/entry_points.txt
tabular2xls-0.4.6.dist-info/top_level.txt
tabular2xls-0.4.6.dist-info/RECORD
