Metadata-Version: 2.1
Name: tabular2xls
Version: 0.4.6
Summary: Convert a file with a LaTeX tabular to Excel
Home-page: https://github.com/eelcovv/tabular2xls
Author: EVLT
Author-email: 
License: MIT
Project-URL: Documentation, https://tabular2xls.readthedocs.io/en/latest/
Platform: any
Classifier: Development Status :: 4 - Beta
Classifier: Programming Language :: Python
License-File: LICENSE.txt
License-File: AUTHORS.rst
Requires-Dist: xlsxwriter
Requires-Dist: matplotlib
Requires-Dist: pandas
Requires-Dist: importlib-metadata; python_version < "3.8"
Provides-Extra: cbs
Requires-Dist: cbsplotlib; extra == "cbs"
Provides-Extra: dev
Requires-Dist: tox; extra == "dev"
Requires-Dist: pre-commit; extra == "dev"
Requires-Dist: black; extra == "dev"
Requires-Dist: pytest; extra == "dev"
Requires-Dist: pytest-cov; extra == "dev"
Provides-Extra: testing
Requires-Dist: setuptools; extra == "testing"
Requires-Dist: pytest; extra == "testing"
Requires-Dist: pytest-cov; extra == "testing"
